aacampaign/__init__.py
aacampaign/admin.py
aacampaign/app_settings.py
aacampaign/apps.py
aacampaign/auth_hooks.py
aacampaign/esi.py
aacampaign/models.py
aacampaign/tasks.py
aacampaign/urls.py
aacampaign/views.py
aacampaign/locale/.gitkeep
aacampaign/management/__init__.py
aacampaign/management/commands/__init__.py
aacampaign/management/commands/aa_campaign_pull.py
aacampaign/management/commands/aa_campaign_setup.py
aacampaign/migrations/0001_initial.py
aacampaign/migrations/0002_campaignkillmail_ship_type_id_and_more.py
aacampaign/migrations/0003_campaignkillmail_ship_group_name.py
aacampaign/migrations/0004_campaignkillmail_final_blow_alliance_id_and_more.py
aacampaign/migrations/0005_campaign_last_run.py
aacampaign/migrations/__init__.py
aacampaign/static/aacampaign/.gitkeep
aacampaign/templates/aacampaign/base.html
aacampaign/templates/aacampaign/campaign_details.html
aacampaign/templates/aacampaign/index.html
aacampaign/tests/__init__.py
aacampaign/tests/test_aa_campaign.py
aa_campaign-1.0.3.dist-info/METADATA
aa_campaign-1.0.3.dist-info/WHEEL
aa_campaign-1.0.3.dist-info/licenses/LICENSE
aa_campaign-1.0.3.dist-info/RECORD
